examples/__init__.py
examples/reader_hydranfc_iso14443_a.py
examples/reader_hydranfc_iso15693.py
examples/reader_hydranfc_v2_iso14443_a.py
examples/reader_hydranfc_v2_iso14443_b.py
examples/reader_hydranfc_v2_iso15693.py
pynfcreader/__init__.py
pynfcreader/devices/__init__.py
pynfcreader/devices/devices.py
pynfcreader/devices/hydra_nfc.py
pynfcreader/devices/hydra_nfc_v2.py
pynfcreader/sessions/__init__.py
pynfcreader/sessions/iso14443/__init__.py
pynfcreader/sessions/iso14443/iso14443.py
pynfcreader/sessions/iso14443/iso14443a.py
pynfcreader/sessions/iso14443/iso14443b.py
pynfcreader/sessions/iso14443/tpdu.py
pynfcreader/sessions/iso14443b/__init__.py
pynfcreader/sessions/iso14443b/iso14443b.py
pynfcreader/sessions/iso14443b/tpdu.py
pynfcreader/sessions/iso15693/__init__.py
pynfcreader/sessions/iso15693/iso15693.py
pynfcreader/sessions/iso15693/requests.py
pynfcreader/tools/__init__.py
pynfcreader/tools/utils.py
tests/__init__.py
tests/conftest.py
tests/tests_iso_14443_a_card_1_hydranfc_v2.py
tests/tests_iso_14443_b_card_2_hydranfc_v2.py
pyNFCReader-1.3.0.dist-info/LICENSE
pyNFCReader-1.3.0.dist-info/METADATA
pyNFCReader-1.3.0.dist-info/WHEEL
pyNFCReader-1.3.0.dist-info/top_level.txt
pyNFCReader-1.3.0.dist-info/RECORD
