Metadata-Version: 2.1
Name: pyNFCReader
Version: 1.3.0
Summary: NFC reader
Home-page: https://github.com/gvinet/pynfcreader
Author: Guillaume VINET
License: UNKNOWN
Platform: UNKNOWN
Classifier: Programming Language :: Python :: 3
Classifier: License :: OSI Approved :: Apache Software License
Classifier: Operating System :: OS Independent
Requires-Dist: pyHydrabus
